braze/__init__.py
braze/sdk/__init__.py
braze/sdk/endpoint.py
braze/sdk/shared/__init__.py
braze/sdk/shared/auth.py
braze/sdk/shared/decorator.py
braze/sdk/shared/functions.py
braze/sdk/validators/__init__.py
braze/sdk/validators/content_blocks.py
braze/sdk/validators/users.py
braze/sdk/validators/users_alias.py
braze/sdk/validators/users_export.py
braze/shared/__init__.py
braze/shared/types.py
braze_client_sdk-1.0.0.dist-info/METADATA
braze_client_sdk-1.0.0.dist-info/WHEEL
braze_client_sdk-1.0.0.dist-info/top_level.txt
braze_client_sdk-1.0.0.dist-info/RECORD
