Metadata-Version: 2.1
Name: braze-client-sdk
Version: 1.0.0
Summary: Creates a SDK for Braze platform
Author: Marcelo Kafels
Project-URL: Homepage, https://github.com/Kafels/braze-python-sdk/
Project-URL: Issues, https://github.com/Kafels/braze-python-sdk/issues
Keywords: braze,sdk
Classifier: Programming Language :: Python :: 3
Classifier: License :: OSI Approved :: MIT License
Classifier: Operating System :: OS Independent
Requires-Python: >=3.9
Requires-Dist: pydantic >=2.6.1
Requires-Dist: requests >=2.31.0
Provides-Extra: dev
Requires-Dist: mock ; extra == 'dev'
Requires-Dist: pytest ; extra == 'dev'
Requires-Dist: pytest-cov ; extra == 'dev'
